{
  "updated_at": "2026-05-22T09:20:40.492135+00:00",
  "bots": [
    {
      "id": "atm-premium-hunter",
      "name": "atm_premium_hunter",
      "description": "Paper trading: atm_premium_hunter",
      "status": "running",
      "pid": 99114,
      "uptime_hours": 6.61,
      "days_running": 0.28,
      "config_name": "atm_premium_hunter",
      "config_status": "paper",
      "config_summary": {
        "iv_rank_threshold": 0.3,
        "target_delta_min": 0.3,
        "target_delta_max": 0.5,
        "max_equity_per_leg": 0.1,
        "starting_equity": 100000.0
      },
      "metrics": {
        "num_trades": 0,
        "win_rate": 0.0,
        "total_return_pct": 0.0,
        "sharpe": 0.0,
        "max_drawdown": 0.0,
        "current_equity": 100000.0,
        "starting_equity": 100000.0
      },
      "readiness": {
        "score": 2,
        "total": 8,
        "ready": false,
        "checks": {
          "min_trades": false,
          "min_days": false,
          "sharpe": false,
          "drawdown": true,
          "win_rate": false,
          "walk_forward": false,
          "reconcile": false,
          "no_kill_switch": true
        }
      },
      "has_open_position": true,
      "open_position": {
        "type": "short_put",
        "strike": 77000.0,
        "expiry": "2026-05-25",
        "dte": 2,
        "pnl_usd": -6.95,
        "pnl_pct": -0.09,
        "current_spot": 77180.88,
        "current_delta": 0.4555,
        "premium_collected": 47.85
      },
      "position_risk": "danger",
      "paused": false
    },
    {
      "id": "capital-roi-v1",
      "name": "capital ROI V1",
      "description": "Paper trading: capital ROI V1",
      "status": "running",
      "pid": 99115,
      "uptime_hours": 6.61,
      "days_running": 0.28,
      "config_name": "capital ROI V1",
      "config_status": "paper",
      "config_summary": {
        "iv_rank_threshold": 0.701,
        "target_delta_min": 0.1883,
        "target_delta_max": 0.4057,
        "max_equity_per_leg": 0.0828,
        "starting_equity": 100000.0
      },
      "metrics": {
        "num_trades": 0,
        "win_rate": 0.0,
        "total_return_pct": 0.0,
        "sharpe": 0.0,
        "max_drawdown": 0.0,
        "current_equity": 100000.0,
        "starting_equity": 100000.0
      },
      "readiness": {
        "score": 2,
        "total": 8,
        "ready": false,
        "checks": {
          "min_trades": false,
          "min_days": false,
          "sharpe": false,
          "drawdown": true,
          "win_rate": false,
          "walk_forward": false,
          "reconcile": false,
          "no_kill_switch": true
        }
      },
      "has_open_position": false,
      "open_position": null,
      "position_risk": "ok",
      "paused": false
    },
    {
      "id": "deep-otm-safety",
      "name": "deep_otm_safety",
      "description": "Paper trading: deep_otm_safety",
      "status": "running",
      "pid": 99128,
      "uptime_hours": 6.61,
      "days_running": 0.28,
      "config_name": "deep_otm_safety",
      "config_status": "paper",
      "config_summary": {
        "iv_rank_threshold": 0.3,
        "target_delta_min": 0.1,
        "target_delta_max": 0.2,
        "max_equity_per_leg": 0.1,
        "starting_equity": 100000.0
      },
      "metrics": {
        "num_trades": 0,
        "win_rate": 0.0,
        "total_return_pct": 0.0,
        "sharpe": 0.0,
        "max_drawdown": 0.0,
        "current_equity": 100000.0,
        "starting_equity": 100000.0
      },
      "readiness": {
        "score": 2,
        "total": 8,
        "ready": false,
        "checks": {
          "min_trades": false,
          "min_days": false,
          "sharpe": false,
          "drawdown": true,
          "win_rate": false,
          "walk_forward": false,
          "reconcile": false,
          "no_kill_switch": true
        }
      },
      "has_open_position": true,
      "open_position": {
        "type": "short_put",
        "strike": 75500.0,
        "expiry": "2026-05-25",
        "dte": 2,
        "pnl_usd": -0.77,
        "pnl_pct": -0.01,
        "current_spot": 77178.62,
        "current_delta": 0.1719,
        "premium_collected": 15.44
      },
      "position_risk": "caution",
      "paused": false
    },
    {
      "id": "long-dte-monthly",
      "name": "long_dte_monthly",
      "description": "Paper trading: long_dte_monthly",
      "status": "running",
      "pid": 99129,
      "uptime_hours": 6.61,
      "days_running": 0.28,
      "config_name": "long_dte_monthly",
      "config_status": "paper",
      "config_summary": {
        "iv_rank_threshold": 0.3,
        "target_delta_min": 0.18,
        "target_delta_max": 0.4,
        "max_equity_per_leg": 0.1,
        "starting_equity": 100000.0
      },
      "metrics": {
        "num_trades": 0,
        "win_rate": 0.0,
        "total_return_pct": 0.0,
        "sharpe": 0.0,
        "max_drawdown": 0.0,
        "current_equity": 100000.0,
        "starting_equity": 100000.0
      },
      "readiness": {
        "score": 2,
        "total": 8,
        "ready": false,
        "checks": {
          "min_trades": false,
          "min_days": false,
          "sharpe": false,
          "drawdown": true,
          "win_rate": false,
          "walk_forward": false,
          "reconcile": false,
          "no_kill_switch": true
        }
      },
      "has_open_position": true,
      "open_position": {
        "type": "short_put",
        "strike": 74000.0,
        "expiry": "2026-06-12",
        "dte": 20,
        "pnl_usd": -6.96,
        "pnl_pct": -0.09,
        "current_spot": 77298.73,
        "current_delta": 0.2959,
        "premium_collected": 124.45
      },
      "position_risk": "caution",
      "paused": false
    },
    {
      "id": "no-hedge-naked",
      "name": "no_hedge_naked",
      "description": "Paper trading: no_hedge_naked",
      "status": "running",
      "pid": 99139,
      "uptime_hours": 6.61,
      "days_running": 0.28,
      "config_name": "no_hedge_naked",
      "config_status": "paper",
      "config_summary": {
        "iv_rank_threshold": 0.3,
        "target_delta_min": 0.18,
        "target_delta_max": 0.4,
        "max_equity_per_leg": 0.1,
        "starting_equity": 100000.0
      },
      "metrics": {
        "num_trades": 0,
        "win_rate": 0.0,
        "total_return_pct": 0.0,
        "sharpe": 0.0,
        "max_drawdown": 0.0,
        "current_equity": 100000.0,
        "starting_equity": 100000.0
      },
      "readiness": {
        "score": 2,
        "total": 8,
        "ready": false,
        "checks": {
          "min_trades": false,
          "min_days": false,
          "sharpe": false,
          "drawdown": true,
          "win_rate": false,
          "walk_forward": false,
          "reconcile": false,
          "no_kill_switch": true
        }
      },
      "has_open_position": true,
      "open_position": {
        "type": "short_put",
        "strike": 76500.0,
        "expiry": "2026-05-25",
        "dte": 2,
        "pnl_usd": -4.63,
        "pnl_pct": -0.06,
        "current_spot": 77187.0,
        "current_delta": 0.3402,
        "premium_collected": 33.19
      },
      "position_risk": "caution",
      "paused": false
    },
    {
      "id": "rl-agent-v1",
      "name": "RL Agent V1",
      "description": "Paper trading: RL Agent V1",
      "status": "running",
      "pid": 99319,
      "uptime_hours": 6.57,
      "days_running": 0.27,
      "config_name": "RL Agent V1",
      "config_status": "paper",
      "config_summary": {
        "iv_rank_threshold": 0.0,
        "target_delta_min": 0.15,
        "target_delta_max": 0.45,
        "max_equity_per_leg": 0.1,
        "starting_equity": 100000.0
      },
      "metrics": {
        "num_trades": 0,
        "win_rate": 0.0,
        "total_return_pct": 0.0,
        "sharpe": 0.0,
        "max_drawdown": 0.0,
        "current_equity": 100000.0,
        "starting_equity": 100000.0
      },
      "readiness": {
        "score": 2,
        "total": 8,
        "ready": false,
        "checks": {
          "min_trades": false,
          "min_days": false,
          "sharpe": false,
          "drawdown": true,
          "win_rate": false,
          "walk_forward": false,
          "reconcile": false,
          "no_kill_switch": true
        }
      },
      "has_open_position": true,
      "open_position": {
        "type": "short_put",
        "strike": 74000.0,
        "expiry": "2026-05-29",
        "dte": 6,
        "pnl_usd": -3.09,
        "pnl_pct": -0.04,
        "current_spot": 77197.76,
        "current_delta": 0.1864,
        "premium_collected": 36.28
      },
      "position_risk": "caution",
      "paused": false
    },
    {
      "id": "short-dte-theta",
      "name": "short_dte_theta",
      "description": "Paper trading: short_dte_theta",
      "status": "running",
      "pid": 99147,
      "uptime_hours": 6.61,
      "days_running": 0.28,
      "config_name": "short_dte_theta",
      "config_status": "paper",
      "config_summary": {
        "iv_rank_threshold": 0.2,
        "target_delta_min": 0.18,
        "target_delta_max": 0.4,
        "max_equity_per_leg": 0.1,
        "starting_equity": 100000.0
      },
      "metrics": {
        "num_trades": 1,
        "win_rate": 0.0,
        "total_return_pct": -0.17,
        "sharpe": 0.0,
        "max_drawdown": 0.0017,
        "current_equity": 99827.6,
        "starting_equity": 100000.0
      },
      "readiness": {
        "score": 2,
        "total": 8,
        "ready": false,
        "checks": {
          "min_trades": false,
          "min_days": false,
          "sharpe": false,
          "drawdown": true,
          "win_rate": false,
          "walk_forward": false,
          "reconcile": false,
          "no_kill_switch": true
        }
      },
      "has_open_position": true,
      "open_position": {
        "type": "short_put",
        "strike": 77000.0,
        "expiry": "2026-05-23",
        "dte": 0,
        "pnl_usd": -3.09,
        "pnl_pct": -0.04,
        "current_spot": 77164.89,
        "current_delta": 0.43,
        "premium_collected": 26.24
      },
      "position_risk": "caution",
      "paused": false
    },
    {
      "id": "close-at-21dte",
      "name": "close_at_21dte",
      "description": "Paper trading: close_at_21dte",
      "status": "running",
      "pid": 62066,
      "uptime_hours": 0.02,
      "days_running": 0.0,
      "config_name": "close_at_21dte",
      "config_status": "paper",
      "config_summary": {
        "iv_rank_threshold": 0.35,
        "target_delta_min": 0.18,
        "target_delta_max": 0.4,
        "max_equity_per_leg": 0.1,
        "starting_equity": 100000.0
      },
      "metrics": {
        "num_trades": 0,
        "win_rate": 0.0,
        "total_return_pct": 0.0,
        "sharpe": 0.0,
        "max_drawdown": 0.0,
        "current_equity": 100000.0,
        "starting_equity": 100000.0
      },
      "readiness": {
        "score": 2,
        "total": 8,
        "ready": false,
        "checks": {
          "min_trades": false,
          "min_days": false,
          "sharpe": false,
          "drawdown": true,
          "win_rate": false,
          "walk_forward": false,
          "reconcile": false,
          "no_kill_switch": true
        }
      },
      "has_open_position": false,
      "open_position": null,
      "position_risk": "ok",
      "paused": false
    },
    {
      "id": "high-iv-only",
      "name": "high_iv_only",
      "description": "Paper trading: high_iv_only",
      "status": "running",
      "pid": 62068,
      "uptime_hours": 0.02,
      "days_running": 0.0,
      "config_name": "high_iv_only",
      "config_status": "paper",
      "config_summary": {
        "iv_rank_threshold": 0.7,
        "target_delta_min": 0.15,
        "target_delta_max": 0.35,
        "max_equity_per_leg": 0.12,
        "starting_equity": 100000.0
      },
      "metrics": {
        "num_trades": 0,
        "win_rate": 0.0,
        "total_return_pct": 0.0,
        "sharpe": 0.0,
        "max_drawdown": 0.0,
        "current_equity": 100000.0,
        "starting_equity": 100000.0
      },
      "readiness": {
        "score": 2,
        "total": 8,
        "ready": false,
        "checks": {
          "min_trades": false,
          "min_days": false,
          "sharpe": false,
          "drawdown": true,
          "win_rate": false,
          "walk_forward": false,
          "reconcile": false,
          "no_kill_switch": true
        }
      },
      "has_open_position": false,
      "open_position": null,
      "position_risk": "ok",
      "paused": false
    },
    {
      "id": "rl-agent-stress",
      "name": "rl_agent_stress",
      "description": "Paper trading: rl_agent_stress",
      "status": "running",
      "pid": 62069,
      "uptime_hours": 0.02,
      "days_running": 0.0,
      "config_name": "rl_agent_stress",
      "config_status": "paper",
      "config_summary": {
        "iv_rank_threshold": 0.0,
        "target_delta_min": 0.15,
        "target_delta_max": 0.45,
        "max_equity_per_leg": 0.15,
        "starting_equity": 100000.0
      },
      "metrics": {
        "num_trades": 0,
        "win_rate": 0.0,
        "total_return_pct": 0.0,
        "sharpe": 0.0,
        "max_drawdown": 0.0,
        "current_equity": 100000.0,
        "starting_equity": 100000.0
      },
      "readiness": {
        "score": 2,
        "total": 8,
        "ready": false,
        "checks": {
          "min_trades": false,
          "min_days": false,
          "sharpe": false,
          "drawdown": true,
          "win_rate": false,
          "walk_forward": false,
          "reconcile": false,
          "no_kill_switch": true
        }
      },
      "has_open_position": true,
      "open_position": {
        "type": "short_put",
        "strike": 74000.0,
        "expiry": "2026-05-29",
        "dte": 6,
        "pnl_usd": 0.0,
        "pnl_pct": 0.0,
        "current_spot": 77196.91,
        "current_delta": 0.1869,
        "premium_collected": 78.74
      },
      "position_risk": "caution",
      "paused": false
    }
  ]
}